resume_parser/__init__.py
resume_parser/parser.py
resume_extractor_cr-0.1.dist-info/LICENSE
resume_extractor_cr-0.1.dist-info/METADATA
resume_extractor_cr-0.1.dist-info/WHEEL
resume_extractor_cr-0.1.dist-info/entry_points.txt
resume_extractor_cr-0.1.dist-info/top_level.txt
resume_extractor_cr-0.1.dist-info/RECORD
