Metadata-Version: 2.1
Name: resume-extractor-cr
Version: 0.1
Summary: A package for parsing resume PDFs.
Home-page: https://github.com/yourusername/resume_parser
Author: Cr
Author-email: Cr@example.com
Classifier: Programming Language :: Python :: 3
Classifier: License :: OSI Approved :: MIT License
Classifier: Operating System :: OS Independent
Requires-Python: >=3.6
License-File: LICENSE
Requires-Dist: pdfplumber
